README.md
setup.py
tangoflux/__init__.py
tangoflux/cli.py
tangoflux/demo.py
tangoflux/model.py
tangoflux/train.py
tangoflux/train_dpo.py
tangoflux/utils.py
tangoflux.egg-info/PKG-INFO
tangoflux.egg-info/SOURCES.txt
tangoflux.egg-info/dependency_links.txt
tangoflux.egg-info/entry_points.txt
tangoflux.egg-info/requires.txt
tangoflux.egg-info/top_level.txt