Metadata-Version: 2.1
Name: tangoflux
Version: 0.1.0
Summary: TangoFlux: Super Fast and Faithful Text to Audio Generation with Flow Matching
Requires-Dist: torch==2.4.0
Requires-Dist: torchaudio==2.4.0
Requires-Dist: torchlibrosa==0.1.0
Requires-Dist: torchvision==0.19.0
Requires-Dist: transformers==4.44.0
Requires-Dist: diffusers==0.30.0
Requires-Dist: accelerate==0.34.2
Requires-Dist: datasets==2.21.0
Requires-Dist: librosa
Requires-Dist: tqdm
Requires-Dist: wandb
Requires-Dist: click
Requires-Dist: gradio
Requires-Dist: torchaudio
